protean_streamlit/__init__.py
protean_streamlit/protean_authenticator.py
protean_streamlit/utils.py
cogrow_protean_streamlit-0.0.1.dist-info/METADATA
cogrow_protean_streamlit-0.0.1.dist-info/WHEEL
cogrow_protean_streamlit-0.0.1.dist-info/top_level.txt
cogrow_protean_streamlit-0.0.1.dist-info/RECORD
