Metadata-Version: 2.4
Name: cogrow-protean-streamlit
Version: 0.0.1
Summary: The official Protean Streamlit library
Author-email: CoGrow <support@cogrow.tech>
License-Expression: MIT
Classifier: Development Status :: 3 - Alpha
Classifier: Intended Audience :: Developers
Classifier: Operating System :: OS Independent
Classifier: Topic :: Software Development :: Libraries :: Python Modules
Requires-Python: >=3.11
Requires-Dist: streamlit<2.0.0,>=1.44.0
Requires-Dist: joserfc>=1.0.4
Requires-Dist: requests>=2
Provides-Extra: build
Requires-Dist: build>=1.2.2; extra == "build"
Provides-Extra: test
Requires-Dist: requests_mock; extra == "test"
Requires-Dist: pytest==8.*; extra == "test"
Requires-Dist: pytest-cov==6.*; extra == "test"
Provides-Extra: dev
Requires-Dist: black; extra == "dev"
Requires-Dist: cogrow-protean-streamlit[build,test]; extra == "dev"
